{"jobTime": ["September 2009 to Present", "August 2006 to May 2007", "November 2006 to January 2007", "January 2005 to August 2006", "July 2004 to August 2006", "June 2003 to February 2005", "March 1997 to May 2003", "July 1993 to May 1996"], "eduDates": ["January 2011 to January 2011", "January 2011 to January 2011", "January 2004 to January 2011", "2000 to 2003", "1990 to 1993"], "name": ["Florentina Galla"], "eduTitle": ["CERTIFICATE in NATURAL HEALTH PROFESSIONALS", "CERTIFICATE in  DENTAL LOCO-ANESTHESIA", "BACHELOR IN SCIENCE, Master degree in Holistic nutrition", "ASSOCIATES in DENTAL HYGIENE", "ASSOCIATES in DENTAL HYGIENE"], "eduSchool": ["NANP", "BCC", "CLAYTON COLLEGE OF NATURAL HEALTH", "BERGEN COMMUNITY COLLEGE", "AT DENTAL TECHNIQUE COLLEGE"]}
