{"jobTime": ["July 2012 to Present", "January 2011 to April 2012", "May 2010 to January 2011", "August 2008 to January 2010", "August 2007 to August 2008", "February 2005 to August 2007", "August 2003 to August 2007", "September 1993 to August 2003", "1984 to 1999"], "eduDates": ["2005", "1999", "1984"], "name": ["Lisa Ivers"], "eduTitle": ["Masters of Art in Education", "Bachelors of Science in Nursing", "College Prep in General"], "eduSchool": ["Almeda University", "Indiana University", "Lakota High School"]}
