{"jobTime": ["January 2012 to August 2012", "May 2009 to May 2011", "May 2009 to May 2011", "May 2009 to May 2011", "May 2009 to June 2009", "October 2007 to March 2009", "June 2006 to December 2007", "August 2002 to May 2006", "August 2001 to September 2002", "October 2000 to July 2001", "March 1999 to August 2000", "June 1998 to August 1998"], "eduDates": ["August 2012 to December 2012", "August 2009 to March 2011", "1998"], "name": ["Melissa Blanchard"], "eduTitle": ["English/Technology", "Education", "Bachelor of Arts in English"], "eduSchool": ["Buffalo State College", "Grand Canyon University", "St. Bonaventure University"]}
