{"jobTime": ["August 2007 to September 2010", "August 1997 to June 2007", "January 1995 to November 1997", "September 1995 to August 1997", "1995 to 1997", "1995 to 1996", "1992 to 1993", "1990 to 1992", "1990 to 1990", "1989 to 1989", "1988 to 1988"], "eduDates": ["July 2005", "November 2002", "January 1976"], "name": ["RoseMary Hatcher"], "eduTitle": ["B.S. in Computer Information Technology", "A.S. in Computer Science"], "eduSchool": ["Belford University", "U.C. Berkeley Teaching Credential Program", "Chicago City College"]}
